mozrepl
