Metadata-Version: 1.1
Name: mozrepl
Version: 1.2.2
Summary: Firefox MozREPL Add-on에 접근하기 위한 인터페이스를 제공합니다.
Home-page: http://thestars3.tistory.com/
Author: 별님
Author-email: w7dn1ng75r@gmail.com
License: GPL v3
Download-URL: https://github.com/Thestars3/pymozrepl/releases
Keywords: mozrepl,firefox
Platform: OS Independent
Classifier: Programming Language :: Python :: 2.7
Classifier: Programming Language :: Python :: 2 :: Only
Classifier: Environment :: Web Environment :: Mozilla
Classifier: Development Status :: 5 - Production/Stable
Classifier: Topic :: Utilities
Classifier: Topic :: Software Development :: Libraries :: Python Modules
Classifier: Operating System :: OS Independent
Classifier: License :: OSI Approved :: GNU General Public License v3 (GPLv3)
